deskviewer/__init__.py
deskviewer/client.py
deskviewer/constant.py
deskviewer/main.py
deskviewer/server.py
deskviewer-0.0.4.dist-info/LICENSE
deskviewer-0.0.4.dist-info/METADATA
deskviewer-0.0.4.dist-info/NOTICE
deskviewer-0.0.4.dist-info/WHEEL
deskviewer-0.0.4.dist-info/entry_points.txt
deskviewer-0.0.4.dist-info/top_level.txt
deskviewer-0.0.4.dist-info/RECORD
