Metadata-Version: 2.1
Name: deskviewer
Version: 0.0.4
Summary: A tool that allows remote computer control.
Home-page: https://github.com/dinceraslancom/deskviewer
Author: Dincer Aslan
Author-email: dinceraslan.com@gmail.com
License: UNKNOWN
Project-URL: Source, https://github.com/dinceraslancom/deskviewer
Platform: UNKNOWN
Classifier: Programming Language :: Python :: 3
Classifier: License :: OSI Approved :: MIT License
Classifier: Operating System :: OS Independent
Requires-Python: >=3.3
License-File: LICENSE
License-File: NOTICE
Requires-Dist: PyQt5 (==5.15.4) ; python_version > "3"
Requires-Dist: numpy (==1.20.3) ; python_version >= "3"
Requires-Dist: mss (==6.1.0) ; python_version >= "3"
Requires-Dist: websockets (==10.0) ; python_version >= "3"
Requires-Dist: pyautogui (==0.9.53) ; python_version >= "3"
Requires-Dist: opencv-python-headless (==4.5.3.56) ; python_version >= "3"
Requires-Dist: asyncio (==3.4.3) ; python_version >= "3.3"
Requires-Dist: uvloop (==0.16.0) ; python_version >= "3.7"
